timechart/__init__.py
timechart/_version.py
timechart/tool.py
timechart/version.py
timechart/data_io/__init__.py
timechart/data_io/settings_exporter.py
timechart/data_io/settings_importer.py
timechart/data_io/importers/__init__.py
timechart/data_io/importers/striptool_config_importer.py
timechart/data_io/importers/timechart_config_importer.py
timechart/displays/__init__.py
timechart/displays/axis_settings_display.py
timechart/displays/chart_data_export_display.py
timechart/displays/curve_settings_display.py
timechart/displays/defaults.py
timechart/displays/main_display.py
timechart/tests/striptool_config_import/__init__.py
timechart/tests/striptool_config_import/test_striptool_config_import.py
timechart/tests/striptool_config_import/data/strip.stp
timechart/tests/striptool_config_import/data/twocurves.stp
timechart/tests/striptool_config_import/expected_output/strip.stp.json
timechart/tests/striptool_config_import/expected_output/twocurves.stp.json
timechart/tests/striptool_config_import/output/strip.stp.json
timechart/tests/striptool_config_import/output/twocurves.stp.json
timechart/utilities/__init__.py
timechart/utilities/utils.py
timechart_launcher/__init__.py
timechart_launcher/main.py
timechart_launcher/icons/charts_128.png
timechart_launcher/icons/charts_16.png
timechart_launcher/icons/charts_24.png
timechart_launcher/icons/charts_256.png
timechart_launcher/icons/charts_32.png
timechart_launcher/icons/charts_64.png
timechart-1.5.3.dist-info/LICENSE.md
timechart-1.5.3.dist-info/METADATA
timechart-1.5.3.dist-info/WHEEL
timechart-1.5.3.dist-info/entry_points.txt
timechart-1.5.3.dist-info/top_level.txt
timechart-1.5.3.dist-info/RECORD
