Metadata-Version: 2.1
Name: timechart
Version: 1.5.3
Summary: Time Chart Tool based on PyDM
Author: SLAC National Accelerator Laboratory
License: Copyright (c) 2023, The Board of Trustees of the Leland Stanford Junior
Classifier: License :: OSI Approved :: BSD License
Classifier: Development Status :: 4 - Beta
Classifier: Programming Language :: Python :: 3.6
Classifier: Programming Language :: Python :: 3.7
Classifier: Programming Language :: Python :: 3.8
Requires-Python: >=3.9
License-File: LICENSE.md
Requires-Dist: pydm >=1.6.0
Requires-Dist: numpy >=1.11.0
Requires-Dist: qtpy
Requires-Dist: pyqtgraph >=0.10.0
Requires-Dist: six
Provides-Extra: doc
Requires-Dist: doctr ; extra == 'doc'
Requires-Dist: sphinx ; extra == 'doc'
Requires-Dist: sphinx-rtd-theme ; extra == 'doc'
Requires-Dist: sphinxcontrib-napoleon ; extra == 'doc'
Provides-Extra: test
Requires-Dist: codecov ; extra == 'test'
Requires-Dist: pytest ; extra == 'test'
Requires-Dist: pytest-qt ; extra == 'test'
Requires-Dist: pytest-cov ; extra == 'test'
